karcher/__init__.py
karcher/auth.py
karcher/cli.py
karcher/consts.py
karcher/countries.py
karcher/device.py
karcher/exception.py
karcher/identifiers.py
karcher/karcher.py
karcher/map.py
karcher/mapdata_pb2.py
karcher/mqtt.py
karcher/user.py
karcher/utils.py
karcher_home-0.5.1.dist-info/LICENSE
karcher_home-0.5.1.dist-info/METADATA
karcher_home-0.5.1.dist-info/WHEEL
karcher_home-0.5.1.dist-info/entry_points.txt
karcher_home-0.5.1.dist-info/top_level.txt
karcher_home-0.5.1.dist-info/RECORD
