Metadata-Version: 2.1
Name: karcher-home
Version: 0.5.1
Summary: Kärcher Home Robots client
Home-page: https://github.com/lafriks/python-karcher
Download-URL: https://github.com/lafriks/python-karcher/releases/download/v0.5.1/karcher-home-0.5.1.tar.gz
Author: Lauris BH
Author-email: lauris@nix.lv
License: MIT
Platform: any
License-File: LICENSE
Requires-Dist: click
Requires-Dist: aiohttp
Requires-Dist: paho-mqtt
Requires-Dist: cryptography
Requires-Dist: protobuf
